app.py
captions.py
captionspackage-0.0.4.dist-info/METADATA
captionspackage-0.0.4.dist-info/WHEEL
captionspackage-0.0.4.dist-info/top_level.txt
captionspackage-0.0.4.dist-info/RECORD
