Metadata-Version: 2.1
Name: captionspackage
Version: 0.0.4
Summary: get captions
Home-page: UNKNOWN
Author: UNKNOWN
Author-email: UNKNOWN
License: UNKNOWN
Platform: UNKNOWN
Requires-Dist: flask
